abstract_queries/__init__.py
abstract_queries/imports.py
abstract_queries/nutest.py
abstract_queries/queriesManager.py
abstract_queries/test.py
abstract_queries/test_queries.py
abstract_queries/py/__init__.py
abstract_queries/py/imports.py
abstract_queries/py/blacklist_queries/__init__.py
abstract_queries/py/blacklist_queries/blacklistManager.py
abstract_queries/py/ip_queries/__init__.py
abstract_queries/py/ip_queries/userIpManager.py
abstract_queries/py/query_utils/__init__.py
abstract_queries/py/query_utils/baseQueryManager.py
abstract_queries/py/query_utils/paths.py
abstract_queries/py/query_utils/query_utils.py
abstract_queries/py/request_queries/__init__.py
abstract_queries/py/request_queries/requestManager.py
abstract_queries/py/table_queries/__init__.py
abstract_queries/py/table_queries/tableManager.py
abstract_queries/py/uploads_queries/__init__.py
abstract_queries/py/uploads_queries/uploadManager.py
abstract_queries/py/user_queries/__init__.py
abstract_queries/py/user_queries/userManager.py
abstract_queries/queries/queries.yaml
abstract_queries/queries/json_queries/blacklistQueries.json
abstract_queries/queries/json_queries/tableQueries.json
abstract_queries/queries/json_queries/uploadsQueries.json
abstract_queries/queries/json_queries/userIpQueries.json
abstract_queries/queries/json_queries/userQueries.json
abstract_queries-0.0.0.109.dist-info/METADATA
abstract_queries-0.0.0.109.dist-info/WHEEL
abstract_queries-0.0.0.109.dist-info/top_level.txt
abstract_queries-0.0.0.109.dist-info/RECORD
